{
  "project_info": {
    "project_number": "502252082685",
    "project_id": "fitflick-17e1d",
    "storage_bucket": "fitflick-17e1d.firebasestorage.app"
  },
  "client": [
    {
      "client_info": {
        "mobilesdk_app_id": "1:502252082685:android:4465f672f4bcf3eff13594",
        "android_client_info": {
          "package_name": "com.example.fitflick"
        }
      },
      "oauth_client": [],
      "api_key": [
        {
          "current_key": "AIzaSyCObmakKDx-cJS7ptBtaxfEnBauQWAqnXc"
        }
      ],
      "services": {
        "appinvite_service": {
          "other_platform_oauth_client": []
        }
      }
    }
  ],
  "configuration_version": "1"
}